tkcustomwindow.py
tkinter_customwindow-0.1.0.dist-info/METADATA
tkinter_customwindow-0.1.0.dist-info/WHEEL
tkinter_customwindow-0.1.0.dist-info/RECORD
