Metadata-Version: 2.1
Name: tkinter-customwindow
Version: 0.1.0
Summary: tkinter titlebar for Windows
Author: XiangQinxi
Author-email: xiangqinxi@outlook.com
Requires-Python: >=3.6,<4.0
Classifier: Programming Language :: Python :: 3
Classifier: Programming Language :: Python :: 3.6
Classifier: Programming Language :: Python :: 3.7
Classifier: Programming Language :: Python :: 3.8
Classifier: Programming Language :: Python :: 3.9
Classifier: Programming Language :: Python :: 3.10
Classifier: Programming Language :: Python :: 3.11
Classifier: Programming Language :: Python :: 3.12
Requires-Dist: pywin32 (>=306,<307)
